azuresphere_device_api/__init__.py
azuresphere_device_api/app.py
azuresphere_device_api/capabilities.py
azuresphere_device_api/certificate.py
azuresphere_device_api/device.py
azuresphere_device_api/devices.py
azuresphere_device_api/error_handler.py
azuresphere_device_api/exceptions.py
azuresphere_device_api/image.py
azuresphere_device_api/manufacturing.py
azuresphere_device_api/network.py
azuresphere_device_api/sideload.py
azuresphere_device_api/utils.py
azuresphere_device_api/validation.py
azuresphere_device_api/wifi.py
azuresphere_device_api/certs/device_rest_api_certificate.pem
azuresphere_device_api-1.1.1.dist-info/LICENSE.txt
azuresphere_device_api-1.1.1.dist-info/METADATA
azuresphere_device_api-1.1.1.dist-info/WHEEL
azuresphere_device_api-1.1.1.dist-info/top_level.txt
azuresphere_device_api-1.1.1.dist-info/RECORD
