Metadata-Version: 2.1
Name: azuresphere-device-api
Version: 1.1.1
Summary: A library for interacting with Azure Sphere devices using the inbuilt REST server.
Author-email: Microsoft <azspheremfrsamplesup@microsoft.com>
Keywords: azure,sphere,device,api
Classifier: License :: OSI Approved :: MIT License
Classifier: Programming Language :: Python :: 3
Classifier: Operating System :: OS Independent
Requires-Python: >=3.8
License-File: LICENSE.txt
Requires-Dist: requests (==2.26.0)
Requires-Dist: requests-toolbelt (>=0.9.1)
